modelo_dados/__init__.py
modelo_dados/comercializacao.py
modelo_dados/importacaoExportacao.py
modelo_dados/processamento.py
modelo_dados/producao.py
site_embrapa/__init__.py
site_embrapa/site_embrapa.py
site_embrapa/vercel_log.py
fiap_lib_grupo56-0.3.27.dist-info/LICENSE
fiap_lib_grupo56-0.3.27.dist-info/METADATA
fiap_lib_grupo56-0.3.27.dist-info/WHEEL
fiap_lib_grupo56-0.3.27.dist-info/top_level.txt
fiap_lib_grupo56-0.3.27.dist-info/RECORD
